kako/__init__.py
kako/config.py
kako/messaging/__init__.py
kako/messaging/capture.py
kako/processor/__init__.py
kako/processor/file.py
kako/processor/sns.py
kako/simulation/__init__.py
kako/simulation/http.py
kako/simulation/https.py
kako/simulation/manifest.py
kako/simulation/telnet.py
kako/simulation/server/__init__.py
kako/simulation/server/error.py
kako/simulation/server/http.py
kako/simulation/server/tcp.py
kako/simulation/server/telnet.py
kako/simulation/system/__init__.py
kako/simulation/system/linux.py
kako-1.1.0.data/scripts/kako-master
kako-1.1.0.dist-info/LICENCE.txt
kako-1.1.0.dist-info/METADATA
kako-1.1.0.dist-info/WHEEL
kako-1.1.0.dist-info/top_level.txt
kako-1.1.0.dist-info/RECORD
