Metadata-Version: 2.1
Name: kako
Version: 1.1.0
Summary: Manifest driven IoT honeypots
Home-page: https://www.github.com/darkarnium/kako
Author: Peter Adkins
Author-email: peter.adkins@kernelpicnic.net
License: MIT
Download-URL: https://github.com/darkarnium/kako/archive/1.1.0.tar.gz
Platform: UNKNOWN
Classifier: Development Status :: 5 - Production/Stable
Classifier: License :: OSI Approved :: MIT License
Classifier: Programming Language :: Python :: 3
Requires-Dist: click (==7.1.2)
Requires-Dist: boto3 (==1.14.48)
Requires-Dist: PyYAML (==5.3.1)
Requires-Dist: requests (==2.24.0)
Requires-Dist: cerberus (==1.3.2)
